affine_rs-0.2.0.dist-info/METADATA
affine_rs-0.2.0.dist-info/WHEEL
affiners/__init__.py
affiners/affiners.cpython-314-darwin.so
affine_rs-0.2.0.dist-info/RECORD
