Metadata-Version: 2.4
Name: affine-rs
Version: 0.2.0
Classifier: Development Status :: 4 - Beta
Classifier: Intended Audience :: Science/Research
Classifier: License :: OSI Approved :: BSD License
Classifier: Programming Language :: Python :: 3
Classifier: Programming Language :: Rust
Classifier: Topic :: Scientific/Engineering :: Image Processing
Requires-Dist: numpy>=1.20
Summary: Fast 3D affine transformations with trilinear interpolation using AVX2/AVX512 SIMD
Keywords: affine,interpolation,simd,avx2,image-processing,numpy
Author: Ilan Theodoro
License: BSD-3-Clause
Requires-Python: >=3.8
